dft/__init__.py
dft/cli/__init__.py
dft/cli/main.py
dft/cli/commands/__init__.py
dft/cli/commands/components.py
dft/cli/commands/deps.py
dft/cli/commands/docs.py
dft/cli/commands/gitignore.py
dft/cli/commands/init.py
dft/cli/commands/run.py
dft/cli/commands/validate.py
dft/core/__init__.py
dft/core/base.py
dft/core/config.py
dft/core/data_packet.py
dft/core/data_packet_simple.py
dft/core/enums.py
dft/core/factory.py
dft/core/microbatch.py
dft/core/pipeline.py
dft/core/pipeline_simple.py
dft/core/runner.py
dft/core/state.py
dft/endpoints/__init__.py
dft/endpoints/clickhouse.py
dft/endpoints/csv.py
dft/endpoints/json.py
dft/endpoints/mysql.py
dft/endpoints/postgresql.py
dft/processors/__init__.py
dft/processors/mad_anomaly_detector.py
dft/processors/validator.py
dft/processors/ab_testing/__init__.py
dft/processors/ab_testing/ab_test_processor.py
dft/processors/ab_testing/models/__init__.py
dft/processors/ab_testing/models/ab_test_config.py
dft/processors/ab_testing/models/fraction.py
dft/processors/ab_testing/models/sample.py
dft/processors/ab_testing/models/test_result.py
dft/processors/ab_testing/stats/__init__.py
dft/processors/ab_testing/stats/base_test.py
dft/processors/ab_testing/stats/bootstrap.py
dft/processors/ab_testing/stats/cuped_ttest.py
dft/processors/ab_testing/stats/ttest.py
dft/processors/ab_testing/stats/ztest.py
dft/processors/ab_testing/utils/__init__.py
dft/processors/ab_testing/utils/bootstrap_utils.py
dft/processors/ab_testing/utils/data_preparers.py
dft/processors/ab_testing/utils/test_factory.py
dft/sources/__init__.py
dft/sources/clickhouse.py
dft/sources/csv.py
dft/sources/google_play.py
dft/sources/json.py
dft/sources/mysql.py
dft/sources/postgresql.py
dft/utils/__init__.py
dft/utils/logging.py
dft/utils/template.py
dft_pipeline-0.3.24.dist-info/METADATA
dft_pipeline-0.3.24.dist-info/WHEEL
dft_pipeline-0.3.24.dist-info/entry_points.txt
dft_pipeline-0.3.24.dist-info/top_level.txt
dft_pipeline-0.3.24.dist-info/RECORD
