Metadata-Version: 2.4
Name: dft-pipeline
Version: 0.3.24
Summary: Data Flow Tools - flexible ETL pipeline framework
Home-page: https://github.com/alexeiveselov92/dft
Author: Alexei Veselov
Author-email: Alexei Veselov <alexei.veselov92@gmail.com>
License: MIT
Project-URL: Homepage, https://github.com/alexeiveselov92/dft
Project-URL: Repository, https://github.com/alexeiveselov92/dft
Project-URL: Issues, https://github.com/alexeiveselov92/dft/issues
Keywords: etl,data-pipeline,data-processing,yaml,analytics
Classifier: Development Status :: 4 - Beta
Classifier: Intended Audience :: Developers
Classifier: License :: OSI Approved :: MIT License
Classifier: Operating System :: OS Independent
Classifier: Programming Language :: Python :: 3
Classifier: Programming Language :: Python :: 3.9
Classifier: Programming Language :: Python :: 3.10
Classifier: Programming Language :: Python :: 3.11
Requires-Python: >=3.9
Requires-Dist: click>=8.0.0
Requires-Dist: pyyaml>=6.0
Requires-Dist: pyarrow>=12.0.0
Requires-Dist: jinja2>=3.0.0
Requires-Dist: python-dotenv>=1.0.0
Requires-Dist: rich>=13.0.0
Requires-Dist: pydantic>=2.0.0
Requires-Dist: numpy>=1.24.0
Requires-Dist: scipy>=1.10.0
Dynamic: author
Dynamic: home-page
Dynamic: requires-python
